timezonefinder/poly_coord_amount.bin
timezonefinder/poly_bounds.bin
timezonefinder/shortcuts.bin
timezonefinder/hole_registry.json
timezonefinder/hole_coord_amount.bin
timezonefinder/poly_adr2data.bin
timezonefinder/py.typed
timezonefinder/poly_zone_ids.bin
timezonefinder/poly_data.bin
timezonefinder/hole_adr2data.bin
timezonefinder/hole_data.bin
timezonefinder/inside_polygon_ext.abi3.so
timezonefinder/timezone_names.json
timezonefinder/poly_nr2zone_id.bin
timezonefinder/inside_poly_extension/inside_polygon_int.c
timezonefinder/inside_poly_extension/inside_polygon_int.h
securetimezonefinder/command_line.py
securetimezonefinder/poly_coord_amount.bin
securetimezonefinder/poly_bounds.bin
securetimezonefinder/hole_registry.json
securetimezonefinder/path_modification.py
securetimezonefinder/hole_coord_amount.bin
securetimezonefinder/poly_adr2data.bin
securetimezonefinder/hole_adr2data.bin
securetimezonefinder/hole_data.bin
securetimezonefinder/hex_helpers.py
securetimezonefinder/configs.py
securetimezonefinder/inside_poly_extension/inside_polygon_int.c
securetimezonefinder/inside_poly_extension/inside_polygon_int.h
securetimezonefinder-1.0.0.dist-info/WHEEL
securetimezonefinder-1.0.0.dist-info/entry_points.txt
securetimezonefinder-1.0.0.dist-info/METADATA
securetimezonefinder-1.0.0.dist-info/LICENSE
securetimezonefinder-1.0.0.dist-info/RECORD
