Metadata-Version: 2.1
Name: securetimezonefinder
Version: 1.0.0
Summary: python package for securely finding the timezone of any point on earth (coordinates) offline
Home-page: https://github.com/SecureTimezones/SecureTimezoneFinder
License: MIT
Keywords: timezone,coordinates,latitude,longitude,location,offline,polygon
Author: SecureTimezones
Requires-Python: >=3.8,<4
Classifier: Development Status :: 5 - Production/Stable
Classifier: Intended Audience :: Developers
Classifier: Intended Audience :: Information Technology
Classifier: License :: OSI Approved :: MIT License
Classifier: Natural Language :: English
Classifier: Operating System :: OS Independent
Classifier: Programming Language :: Python :: 3
Classifier: Programming Language :: Python :: 3.8
Classifier: Programming Language :: Python :: 3.9
Classifier: Programming Language :: Python :: 3.10
Classifier: Programming Language :: Python :: 3.11
Classifier: Programming Language :: Python :: 3.12
Classifier: Programming Language :: Python :: 3.13
Classifier: Topic :: Software Development :: Localization
Provides-Extra: numba
Provides-Extra: pytz
Requires-Dist: cffi (>=1.15.1,<2)
Requires-Dist: h3 (>4)
Requires-Dist: numba (>=0.56,<1) ; (python_version < "3.12") and (extra == "numba")
Requires-Dist: numba (>=0.59,<1) ; (python_version >= "3.12") and (extra == "numba")
Requires-Dist: numpy (>=1.21,<3) ; python_version < "3.9"
Requires-Dist: numpy (>=1.23,<3) ; python_version >= "3.9"
Requires-Dist: pytz (>=2022.7.1) ; extra == "pytz"
Project-URL: Documentation, https://github.com/SecureTimezones/SecureTimezoneFinder
Project-URL: Repository, https://github.com/SecureTimezones/SecureTimezoneFinder
